weird_json/__init__.py
weird_json/js.py
weird_json-0.1.0.dist-info/METADATA
weird_json-0.1.0.dist-info/WHEEL
weird_json-0.1.0.dist-info/top_level.txt
weird_json-0.1.0.dist-info/RECORD
