Metadata-Version: 2.1
Name: weird-json
Version: 0.1.0
Summary: My implementation for JavaScript Object Notation
Author: weerdy15
Author-email: igorekkrupskij@gmail.com
License: UNKNOWN
Project-URL: Bug Tracker, https://github.com/weerdy15/weird_json/issues
Platform: UNKNOWN
Classifier: Programming Language :: Python :: 3
Classifier: Programming Language :: Python :: 3.7
Classifier: Programming Language :: Python :: 3.8
Classifier: Programming Language :: Python :: 3.9
Classifier: Programming Language :: Python :: 3.10
Classifier: License :: OSI Approved :: MIT License
Classifier: Operating System :: OS Independent
Requires-Python: >=3.7
